mcp_local_repo_analyzer/__init__.py
mcp_local_repo_analyzer/cli.py
mcp_local_repo_analyzer/main.py
mcp_local_repo_analyzer/run_http_server.py
mcp_local_repo_analyzer/services/git/__init__.py
mcp_local_repo_analyzer/services/git/change_detector.py
mcp_local_repo_analyzer/services/git/diff_analyzer.py
mcp_local_repo_analyzer/services/git/status_tracker.py
mcp_local_repo_analyzer/tools/__init__.py
mcp_local_repo_analyzer/tools/staging_area.py
mcp_local_repo_analyzer/tools/summary.py
mcp_local_repo_analyzer/tools/unpushed_commits.py
mcp_local_repo_analyzer/tools/working_directory.py
mcp_shared_lib/__init__.py
mcp_shared_lib/config/__init__.py
mcp_shared_lib/config/base.py
mcp_shared_lib/config/git_analyzer.py
mcp_shared_lib/models/__init__.py
mcp_shared_lib/models/analysis/__init__.py
mcp_shared_lib/models/analysis/categorization.py
mcp_shared_lib/models/analysis/repository.py
mcp_shared_lib/models/analysis/results.py
mcp_shared_lib/models/analysis/risk.py
mcp_shared_lib/models/base/common.py
mcp_shared_lib/models/base/types.py
mcp_shared_lib/models/git/changes.py
mcp_shared_lib/models/git/commits.py
mcp_shared_lib/models/git/files.py
mcp_shared_lib/models/git/repository.py
mcp_shared_lib/py.typed
mcp_shared_lib/server/__init__.py
mcp_shared_lib/server/runner.py
mcp_shared_lib/services/__init__.py
mcp_shared_lib/services/git/git_client.py
mcp_shared_lib/test_utils/__init__.py
mcp_shared_lib/test_utils/factories/__init__.py
mcp_shared_lib/test_utils/factories/analysis.py
mcp_shared_lib/test_utils/factories/base.py
mcp_shared_lib/test_utils/factories/files.py
mcp_shared_lib/test_utils/factories/git.py
mcp_shared_lib/test_utils/factories/recommendations.py
mcp_shared_lib/test_utils/factories/scenarios.py
mcp_shared_lib/test_utils/factories/tools.py
mcp_shared_lib/tools/__init__.py
mcp_shared_lib/tools/base.py
mcp_shared_lib/transports/__init__.py
mcp_shared_lib/transports/base.py
mcp_shared_lib/transports/config.py
mcp_shared_lib/transports/factory.py
mcp_local_repo_analyzer-0.1.0.dist-info/METADATA
mcp_local_repo_analyzer-0.1.0.dist-info/WHEEL
mcp_local_repo_analyzer-0.1.0.dist-info/entry_points.txt
mcp_local_repo_analyzer-0.1.0.dist-info/RECORD
