Metadata-Version: 2.3
Name: mcp-local-repo-analyzer
Version: 0.1.0
Summary: MCP server for analyzing outstanding git changes in repositories
License: MIT
Keywords: mcp,model-context-protocol,git,repository-analysis,mcp-server
Author: Manav Gupta
Author-email: manavg@gmail.com
Requires-Python: >=3.10,<4.0
Classifier: Development Status :: 3 - Alpha
Classifier: Intended Audience :: Developers
Classifier: License :: OSI Approved :: MIT License
Classifier: Operating System :: OS Independent
Classifier: Programming Language :: Python :: 3
Classifier: Programming Language :: Python :: 3.10
Classifier: Programming Language :: Python :: 3.11
Classifier: Programming Language :: Python :: 3.12
Classifier: Programming Language :: Python :: 3.13
Classifier: Topic :: Software Development :: Libraries :: Application Frameworks
Classifier: Topic :: Software Development :: Version Control :: Git
Requires-Dist: click (>=8.1.7,<9.0.0)
Requires-Dist: fastapi (>=0.116.1,<0.117.0)
Requires-Dist: fastmcp (>=2.10.6,<3.0.0)
Requires-Dist: gitpython (>=3.1.40,<4.0.0)
Requires-Dist: pathlib (>=1.0.1,<2.0.0)
Requires-Dist: pydantic-settings (>=2.10.1,<3.0.0)
Requires-Dist: pydantic[mypy] (>=2.11.7,<3.0.0)
Requires-Dist: sse-starlette (>=2.4.1,<3.0.0)
Requires-Dist: typing-extensions (>=4.8.0,<5.0.0)
Requires-Dist: uvicorn (>=0.35.0,<0.36.0)
Project-URL: Documentation, https://github.com/manavgup/mcp_local_repo_analyzer#readme
Project-URL: Homepage, https://github.com/manavgup/mcp_local_repo_analyzer
Project-URL: Repository, https://github.com/manavgup/mcp_local_repo_analyzer
